freedompop/__init__.py
freedompop/__main__.py
freedompop-1.1.1.dist-info/LICENSE
freedompop-1.1.1.dist-info/METADATA
freedompop-1.1.1.dist-info/WHEEL
freedompop-1.1.1.dist-info/top_level.txt
freedompop-1.1.1.dist-info/RECORD
