Metadata-Version: 2.1
Name: freedompop
Version: 1.1.1
Summary: Unofficial FreedomPop client library
Home-page: https://github.com/jaraco/freedompop
Author: Jason R. Coombs
Author-email: jaraco@jaraco.com
License: UNKNOWN
Platform: UNKNOWN
Classifier: Development Status :: 5 - Production/Stable
Classifier: Intended Audience :: Developers
Classifier: License :: OSI Approved :: MIT License
Classifier: Programming Language :: Python :: 3
Requires-Python: >=3.6
Requires-Dist: autocommand
Requires-Dist: requests-toolbelt
Requires-Dist: tempora
Requires-Dist: jaraco.functools
Provides-Extra: docs
Requires-Dist: sphinx ; extra == 'docs'
Requires-Dist: jaraco.packaging (>=3.2) ; extra == 'docs'
Requires-Dist: rst.linker (>=1.9) ; extra == 'docs'
Provides-Extra: testing
Requires-Dist: pytest (!=3.7.3,>=3.5) ; extra == 'testing'
Requires-Dist: pytest-checkdocs ; extra == 'testing'
Requires-Dist: pytest-flake8 ; extra == 'testing'
Requires-Dist: pytest-black-multipy ; extra == 'testing'
Requires-Dist: pytest-cov ; extra == 'testing'
